community_broker_score/__init__.py
community_broker_score/community_broker_score.py
Community_Broker_Score-0.1.5.dist-info/LICENSE
Community_Broker_Score-0.1.5.dist-info/METADATA
Community_Broker_Score-0.1.5.dist-info/WHEEL
Community_Broker_Score-0.1.5.dist-info/top_level.txt
Community_Broker_Score-0.1.5.dist-info/RECORD
