Metadata-Version: 2.1
Name: Community-Broker-Score
Version: 0.1.5
Summary: Package to detect and find the local community broker score with a known partition
Home-page: https://github.com/Masarah/community_broker_score
Author: Masarah Paquet-Clouston
Author-email: m.paquet-clouston@umontreal.ca
Project-URL: Bug Tracker, https://github.com/Masarah/community_broker_score/issues
Classifier: Programming Language :: Python :: 3
Classifier: License :: OSI Approved :: MIT License
Classifier: Operating System :: OS Independent
Requires-Python: >=3.6
License-File: LICENSE
